{
  "intro": "Hi",
  "heroPhoto": {
    "src": "../../images/lego-dummy.png",
    "alt": "My Photo"
  },
  "image": {
    "src": "../../images/waving-hand.png",
    "alt": "Waving Hand Emoji"
  },
  "title": "Welcome",
  "subtitle": {
    "prefix": "to ",
    "highlight": "CAME TechGroup",
    "suffix": "."
  },
  "description": "We are a group of skilled individuals who have joined forces to create solutions for your business.",
  "socialProfiles": {
    "from": ["LinkedIn", "Medium", "Github", "Mail"],
    "showIcons": false
  }
}
